django_xlsx_serializer-1.1.0.dist-info/licenses/LICENSE
xlsx_serializer/__init__.py
xlsx_serializer/apps.py
xlsx_serializer/core.py
xlsx_serializer/py.typed
django_xlsx_serializer-1.1.0.dist-info/METADATA
django_xlsx_serializer-1.1.0.dist-info/WHEEL
django_xlsx_serializer-1.1.0.dist-info/top_level.txt
django_xlsx_serializer-1.1.0.dist-info/RECORD
