Metadata-Version: 2.4
Name: django-xlsx-serializer
Version: 1.1.0
Summary: Load/dump Django models from/to Excel 2007+ workbooks
Author-email: Kamil Paduszyński <92403542+paduszyk@users.noreply.github.com>
Project-URL: Repository, https://github.com/paduszyk/django-xlsx-serializer
Keywords: django,django-application,excel,excel-export,excel-import
Classifier: Environment :: Web Environment
Classifier: Framework :: Django
Classifier: Framework :: Django :: 3.2
Classifier: Framework :: Django :: 4.0
Classifier: Framework :: Django :: 4.1
Classifier: Framework :: Django :: 4.2
Classifier: Framework :: Django :: 5.0
Classifier: Framework :: Django :: 5.1
Classifier: Framework :: Django :: 5.2
Classifier: Intended Audience :: Developers
Classifier: License :: OSI Approved :: MIT License
Classifier: Operating System :: OS Independent
Classifier: Programming Language :: Python
Classifier: Programming Language :: Python :: 3
Classifier: Programming Language :: Python :: 3 :: Only
Classifier: Programming Language :: Python :: 3.9
Classifier: Programming Language :: Python :: 3.10
Classifier: Programming Language :: Python :: 3.11
Classifier: Programming Language :: Python :: 3.12
Classifier: Programming Language :: Python :: 3.13
Classifier: Topic :: Software Development :: Libraries :: Python Modules
Requires-Python: >=3.9
License-File: LICENSE
Requires-Dist: django<5.3,>=3.2
Requires-Dist: openpyxl<4
Requires-Dist: typing-extensions<5
Provides-Extra: dev
Requires-Dist: commitizen<4; extra == "dev"
Requires-Dist: django-stubs[compatible-mypy]<6; extra == "dev"
Requires-Dist: nox; extra == "dev"
Requires-Dist: pre-commit<4; extra == "dev"
Requires-Dist: pytest<9; extra == "dev"
Requires-Dist: pytest-cov<6; extra == "dev"
Requires-Dist: pytest-django<5; extra == "dev"
Requires-Dist: pytest-custom-exit-code<1; extra == "dev"
Requires-Dist: psycopg2-binary<3; extra == "dev"
Requires-Dist: python-dotenv<2; extra == "dev"
Requires-Dist: ruff<1; extra == "dev"
Requires-Dist: types-openpyxl<4; extra == "dev"
Dynamic: license-file
